{
  "Electronics": [
    {"id": 1, "name": "PS6", "image": "/products/item (42).jpg", "price": "$420", "rating": 4.5, "review": "Fast performance with smooth connectivity and clear HD quality"},
    {"id": 2, "name": "JBL Bluetooth Speaker", "image": "/products/item (40).jpg", "price": "$65", "rating": 4.3, "review": "Very loud with clear and balanced sound output"},
    {"id": 3, "name": "Wireless Headphones", "image": "/products/item (37).jpg", "price": "$95", "rating": 4.6, "review": "Comfortable fit with deep bass and long battery life"},
    {"id": 4, "name": "All iPhone Products", "image": "/products/item (28).jpg", "price": "$35", "rating": 4.2, "review": "Reliable accessories with smooth performance"},
    {"id": 5, "name": "HP Laptop", "image": "/products/l.jpg", "price": "$40", "rating": 4.1, "review": "Great for everyday tasks and long working hours"},
    {"id": 6, "name": "iPhone 13", "image": "/products/0o.jpg", "price": "$799", "rating": 4.8, "review": "Excellent camera quality with fast and smooth performance"},
    {"id": 7, "name": "Apple Laptop", "image": "/products/ko.jpg", "price": "$950", "rating": 4.4, "review": "Powerful and efficient for work, coding, and study"},
    {"id": 8, "name": "Headphones", "image": "/products/item (7).jpg", "price": "$160", "rating": 4.8, "review": "Clear sound with a calm and immersive listening experience"},
    {"id": 9, "name": "AI Glass", "image": "/products/u8.jpg", "price": "$35", "rating": 4.2, "review": "Smart features with a modern and lightweight design"},
    {"id": 10, "name": "Gaming Keyboard", "image": "/products/item (24).jpg", "price": "$80", "rating": 4.5, "review": "Responsive keys with smooth typing and gaming experience"},
    {"id": 11, "name": "Pink Laptop", "image": "/products/ip.jpg", "price": "$85", "rating": 4.5, "review": "Stylish design with reliable performance for daily use"},
    {"id": 12, "name": "Electric Walk Scooter", "image": "/products/m.jpg", "price": "$60", "rating": 4.4, "review": "Smooth ride with fast charging and good battery life"}
  ],

  "shoes": [
    {"id": 13, "name": "Channel Bag and Female Easy-Wear", "image": "/products/item (4).jpg", "price": "$130", "rating": 4.6, "review": "Classic fashion combo with a comfortable feel"},
    {"id": 14, "name": "Nike Running Shoes", "image": "/images/pngegg (7).png", "price": "$85", "rating": 4.3, "review": "Lightweight and perfect for running and workouts"},
    {"id": 15, "name": "Reebok Classic Sneakers", "image": "/images/5.png", "price": "$90", "rating": 4.2, "review": "Timeless design with comfortable everyday wear"},
    {"id": 16, "name": "Converse High Top", "image": "/images/3.jpg", "price": "$75", "rating": 4.1, "review": "Stylish casual sneakers for everyday outfits"},
    {"id": 17, "name": "Men Golf Polo", "image": "/images/90.jpg", "price": "$95", "rating": 4.4, "review": "Comfortable fit with durable material quality"},
    {"id": 18, "name": "Sweater Hooded", "image": "/images/ju.jpg", "price": "$160", "rating": 4.8, "review": "Warm and premium quality with a stylish look"},
    {"id": 19, "name": "Adult Plain T-Shirt", "image": "/images/du.jpg", "price": "$160", "rating": 4.8, "review": "Simple, clean design with a comfortable fit"},
    {"id": 20, "name": "Cozy Hoodie", "image": "/images/op.jpg", "price": "$110", "rating": 4.7, "review": "Very soft and comfortable for daily wear"},
    {"id": 21, "name": "Channel Bag and Heels", "image": "/products/item (3).jpg", "price": "$160", "rating": 4.8, "review": "Premium combo with elegant style"},
    {"id": 22, "name": "Women Fitting Shirt", "image": "/images/gh.jpg", "price": "$110", "rating": 4.7, "review": "Perfect fit with breathable fabric"},
    {"id": 23, "name": "Men Athletic Wear", "image": "/images/9l.jpg", "price": "$160", "rating": 4.8, "review": "Great for workouts with flexible material"},
    {"id": 24, "name": "Stanley Shoes with Bag", "image": "/products/item (38).jpg", "price": "$110", "rating": 4.7, "review": "Comfortable shoes with a stylish matching bag"}
  ],

  "HomeItems": [
    {"id": 25, "name": "Comfortable Sofa Chair", "image": "/products/p2.png", "price": "$320", "rating": 4.6, "review": "Extremely comfortable with modern design"},
    {"id": 26, "name": "Kitchen Blender", "image": "/products/b.jpg", "price": "$70", "rating": 4.2, "review": "Powerful blender perfect for smoothies and juices"},
    {"id": 27, "name": "Set of Pots", "image": "/products/ui.jpg", "price": "$28", "rating": 4.1, "review": "Durable and simple cookware set for daily use"},
    {"id": 28, "name": "Electric Kettle", "image": "/products/h.jpg", "price": "$45", "rating": 4.4, "review": "Boils water quickly and safely"},
    {"id": 29, "name": "Sofa with Lamp", "image": "/products/p4.png", "price": "$95", "rating": 4.3, "review": "Perfect combination for a cozy living space"},
    {"id": 30, "name": "Smart TV", "image": "/products/item (39).jpg", "price": "$50", "rating": 4.4, "review": "Clear display with smart features for entertainment"},
    {"id": 31, "name": "Pink Pot", "image": "/products/0.jpg", "price": "$160", "rating": 4.8, "review": "Beautiful design with strong build quality"},
    {"id": 32, "name": "Butterfly Pillow", "image": "/products/cv.jpg", "price": "$35", "rating": 4.3, "review": "Soft, cute, and perfect for decoration"},
    {"id": 33, "name": "Duvet", "image": "/products/item (25).jpg", "price": "$85", "rating": 4.5, "review": "Warm and comfortable for all seasons"},
    {"id": 34, "name": "Refrigerator", "image": "/products/r.jpg", "price": "$60", "rating": 4.4, "review": "Cools quickly with good storage capacity"},
    {"id": 35, "name": "Air Fryer", "image": "/products/yh.jpg", "price": "$85", "rating": 4.5, "review": "Fast cooking with less oil and easy to use"},
    {"id": 36, "name": "Coffee Dispenser", "image": "/products/des..jpg", "price": "$85", "rating": 4.5, "review": "Great for making different types of coffee"}
  ],

  "MoreProduct": [
    {"id": 37, "name": "Luxury Tower", "image": "/products/0..jpg", "price": "$85", "rating": 4.5, "review": "Stylish and modern design for home decor"},
    {"id": 38, "name": "Women Crocs", "image": "/products/rs.jpg", "price": "$60", "rating": 4.4, "review": "Very comfortable and fashionable"},
    {"id": 39, "name": "Sandal Fit", "image": "/products/444.jpg", "price": "$85", "rating": 4.5, "review": "Lightweight and perfect for casual wear"},
    {"id": 40, "name": "Gucci Shoe Set", "image": "/products/item (13).jpg", "price": "$55", "rating": 4.6, "review": "Stylish and durable premium design"},
    {"id": 41, "name": "Women Handbag and Shoe", "image": "/products/item (10).jpg", "price": "$60", "rating": 4.4, "review": "Fashionable combo with strong material"},
    {"id": 42, "name": "Gold Watch", "image": "/products/ii.jpg", "price": "$85", "rating": 4.5, "review": "Elegant design with long-lasting shine"},
    {"id": 43, "name": "Modern Cooking Pot Set", "image": "/products/455.jpg", "price": "$55", "rating": 4.6, "review": "Durable set perfect for everyday cooking"},
    {"id": 44, "name": "Diamond Necklace", "image": "/products/item (45).jpg", "price": "$35", "rating": 4.2, "review": "Beautiful and shiny for special occasions"},
    {"id": 45, "name": "Pink Bag", "image": "/products/item (46).jpg", "price": "$80", "rating": 4.5, "review": "Trendy design with enough storage space"},
    {"id": 46, "name": "Pink Headphone", "image": "/products/j.jpg", "price": "$85", "rating": 4.5, "review": "Stylish with clear and balanced sound"},
    {"id": 47, "name": "Refrigerator", "image": "/products/r.jpg", "price": "$60", "rating": 4.4, "review": "Efficient cooling with low energy usage"},
    {"id": 48, "name": "Gaming Keyboard", "image": "/products/lk.jpg", "price": "$80", "rating": 4.5, "review": "Smooth typing with responsive keys"},
    {"id": 49, "name": "White Sofa", "image": "/products/p6.png", "price": "$85", "rating": 4.5, "review": "Comfortable and modern for any living room"},
    {"id": 50, "name": "Ring Light", "image": "/products/pl.jpg", "price": "$60", "rating": 4.4, "review": "Bright and perfect for photos and videos"},
    {"id": 51, "name": "White Headset", "image": "/products/66.jpg", "price": "$85", "rating": 4.5, "review": "Clean design with good sound quality"},
    {"id": 52, "name": "Shoe", "image": "/products/w.jpg", "price": "$60", "rating": 4.4, "review": "Simple and comfortable for everyday use"}
    
    
  ],

   "FeatureProduct": [
    { "id": 53, "name": "Smart Watch"," price": "$55", "image": "/products/item (22).jpg" },
    { "id": 54, "name": "skatting shoes", "price": "$80", "image": "/products/item (21).jpg"},
    { "id": 55, "name": "Laptop gadget", "price": "$45", "image": "/products/item (16).jpg" },
    { "id": 56, "name": "Laptop", "price": "$55", "image": "/products/l8.jpg" },
    { "id": 57, "name": "Gaming TV", "price": "$40"," image": "/products/item (5).jpg" },
    {" id": 58," name": "iphone", "price": "$15", "image": "/products/item (17).jpg" },
    { "id": 59," name": "Bluetooth Speaker", "price": "$55", "image": "/products/tg.jpg" },
    { "id": 60, "name": "Game pad", "price": "$40", "image": "/products/item (24).jpg" }
  ]


}

